watermarklab/__init__.py
watermarklab/attackers/__init__.py
watermarklab/attackers/attackerloader.py
watermarklab/attackers/diffattackers/__init__.py
watermarklab/attackers/diffattackers/diffattackers.py
watermarklab/attackers/diffattackers/utils_printcapture.py
watermarklab/attackers/testattackers/__init__.py
watermarklab/attackers/testattackers/advattack.py
watermarklab/attackers/testattackers/blur.py
watermarklab/attackers/testattackers/color.py
watermarklab/attackers/testattackers/compression.py
watermarklab/attackers/testattackers/geometric.py
watermarklab/attackers/testattackers/noise.py
watermarklab/attackers/testattackers/regeneration.py
watermarklab/datasets/__init__.py
watermarklab/datasets/datasets.py
watermarklab/draw/__init__.py
watermarklab/draw/func.py
watermarklab/draw/utils.py
watermarklab/laboratories/IGW_func.py
watermarklab/laboratories/PGW_func.py
watermarklab/laboratories/__init__.py
watermarklab/laboratories/func.py
watermarklab/laboratories/utils.py
watermarklab/metrics/__init__.py
watermarklab/metrics/metrics4test.py
watermarklab/metrics/metrics4use.py
watermarklab/steganography/__init__.py
watermarklab/steganography/isteganogan.py
watermarklab/tools/AC.py
watermarklab/tools/PEE.py
watermarklab/tools/__init__.py
watermarklab/utils/__init__.py
watermarklab/utils/logger.py
watermarklab/utils/parameters.py
watermarklab/utils/basemodel/__init__.py
watermarklab/utils/data/__init__.py
watermarklab/watermarks/__init__.py
watermarklab/watermarks/IGWs/__init__.py
watermarklab/watermarks/IGWs/gaussianshading.py
watermarklab/watermarks/IGWs/stablesignature.py
watermarklab/watermarks/IGWs/treering.py
watermarklab/watermarks/PGWs/__init__.py
watermarklab/watermarks/PGWs/dctDwt.py
watermarklab/watermarks/PGWs/dctDwtSvd.py
watermarklab/watermarks/PGWs/invismark.py
watermarklab/watermarks/PGWs/rivaGAN.py
watermarklab/watermarks/PGWs/stegastamp.py
watermarklab/watermarks/PGWs/trustmark.py
watermarklab/watermarks/PGWs/vine.py
watermarklab-0.1.22.dist-info/licenses/LICENSE
watermarklab-0.1.22.dist-info/METADATA
watermarklab-0.1.22.dist-info/WHEEL
watermarklab-0.1.22.dist-info/top_level.txt
watermarklab-0.1.22.dist-info/RECORD
