Metadata-Version: 2.4
Name: watermarklab
Version: 0.1.22
Summary: A comprehensive toolkit for robust image watermarking benchmarking and development.
Home-page: https://watermarklab.github.io
Author: Jiale chen
Author-email: chenoly@outlook.com
Project-URL: Bug Reports, https://github.com/watermarklab/watermarklab.github.io/issues
Project-URL: Source, https://github.com/watermarklab/watermarklab.github.io
Project-URL: Documentation, https://watermarklab.github.io/pages/api-document.html
Keywords: robust image watermarking,robustness testing
Classifier: Development Status :: 3 - Alpha
Classifier: Intended Audience :: Science/Research
Classifier: Intended Audience :: Developers
Classifier: Topic :: Scientific/Engineering :: Image Processing
Classifier: Topic :: Security :: Cryptography
Classifier: License :: OSI Approved :: MIT License
Classifier: Programming Language :: Python :: 3
Classifier: Programming Language :: Python :: 3.9
Classifier: Programming Language :: Python :: 3.10
Classifier: Programming Language :: Python :: 3.11
Classifier: Operating System :: OS Independent
Requires-Python: >=3.9
License-File: LICENSE
Requires-Dist: numpy>=1.21.0
Requires-Dist: pillow>=8.0.0
Requires-Dist: clean-fid>=0.1.35
Requires-Dist: lpips>=0.1.4
Requires-Dist: opencv-python>=4.5.0
Requires-Dist: kornia>=0.6.0
Requires-Dist: psutil>=5.8.0
Requires-Dist: nvidia-ml-py>=12.0.0
Requires-Dist: matplotlib>=3.5.0
Requires-Dist: PyWavelets>=1.1.0
Requires-Dist: onnxruntime-gpu>=1.9.0
Requires-Dist: diffusers>=0.20.0
Requires-Dist: pyfiglet>=0.7.0
Requires-Dist: pycryptodome>=3.10.0
Requires-Dist: transformers>=4.20.0
Requires-Dist: accelerate>=0.15.0
Requires-Dist: colorama>=0.4.4
Requires-Dist: seaborn>=0.13.2
Requires-Dist: scikit-learn>=1.0.0
Requires-Dist: compressai>=1.2.0
Requires-Dist: py-cpuinfo>=8.0.0
Requires-Dist: peft>=0.17.1
Dynamic: author
Dynamic: author-email
Dynamic: classifier
Dynamic: description
Dynamic: description-content-type
Dynamic: home-page
Dynamic: keywords
Dynamic: license-file
Dynamic: project-url
Dynamic: requires-dist
Dynamic: requires-python
Dynamic: summary
